README.rst
setup.cfg
setup.py
src/parseudev/__init__.py
src/parseudev/_devlink.py
src/parseudev/_dm_uuid.py
src/parseudev/_id_path.py
src/parseudev/_lookup.py
src/parseudev/_pci_address.py
src/parseudev/_version.py
src/parseudev.egg-info/PKG-INFO
src/parseudev.egg-info/SOURCES.txt
src/parseudev.egg-info/dependency_links.txt
src/parseudev.egg-info/top_level.txt
src/parseudev/_shared/__init__.py
src/parseudev/_shared/_shared.py
src/parseudev/_shared/parse.py